setup.py
My_Server_Student.egg-info/PKG-INFO
My_Server_Student.egg-info/SOURCES.txt
My_Server_Student.egg-info/dependency_links.txt
My_Server_Student.egg-info/requires.txt
My_Server_Student.egg-info/top_level.txt
server/__init__.py
server/server.py
server/logs/__init__.py
server/logs/config_client_log.py
server/logs/config_server_log.py
server/server/__init__.py
server/server/add_user.py
server/server/config_window.py
server/server/core.py
server/server/database.py
server/server/main_window.py
server/server/remove_user.py
server/server/stat_window.py
server/system/__init__.py
server/system/config.py
server/system/decos.py
server/system/descryptors.py
server/system/errors.py
server/system/metaclasses.py
server/system/utils.py
server/unit_tests/__init__.py
server/unit_tests/test_client.py
server/unit_tests/test_utils.py