Metadata-Version: 1.0
Name: My-Server-Student
Version: 0.0.1
Summary: Messenger_Server
Home-page: UNKNOWN
Author: Student
Author-email: user@user.ru
License: UNKNOWN
Platform: UNKNOWN
